hyperai/__init__.py
hyperai-0.0.1.dist-info/METADATA
hyperai-0.0.1.dist-info/WHEEL
hyperai-0.0.1.dist-info/licenses/LICENSE
hyperai-0.0.1.dist-info/RECORD
