Metadata-Version: 2.4
Name: hyperai
Version: 0.0.1
Summary: HyperAI library for Python
Project-URL: Homepage, https://github.com/hyperai/python-hyperai
Project-URL: Repository, https://github.com/hyperai/python-hyperai
Author-email: HyperAI <hi@hyper.ai>
License-Expression: MIT
License-File: LICENSE
Keywords: hyperai
Classifier: Development Status :: 1 - Planning
Classifier: Intended Audience :: Developers
Classifier: License :: OSI Approved :: MIT License
Classifier: Programming Language :: Python :: 3
Classifier: Programming Language :: Python :: 3.8
Classifier: Programming Language :: Python :: 3.9
Classifier: Programming Language :: Python :: 3.10
Classifier: Programming Language :: Python :: 3.11
Classifier: Programming Language :: Python :: 3.12
Requires-Python: >=3.8
